gitpoll/__init__.py
gitpoll/args.py
gitpoll/config.py
gitpoll/git.py
gitpoll/log.py
gitpoll/main.py
gitpoll/shell.py
gitpoll/version.py
gitpoll-1.11.1.dist-info/LICENSE
gitpoll-1.11.1.dist-info/METADATA
gitpoll-1.11.1.dist-info/WHEEL
gitpoll-1.11.1.dist-info/entry_points.txt
gitpoll-1.11.1.dist-info/top_level.txt
gitpoll-1.11.1.dist-info/RECORD
